{
    "meta":{
        "display_name": "normalized features (or)",
        "description":"certifies that weather or not all the scalar features are normalized properly",
        "tags": ["robust"],
        "level":["1"]
    },

    "condition": {
            "op":"or" ,
            "terms": [              
                [ "&basic_robustness > normalized_feature_01" , "==" , "True" ],
                [ "&basic_robustness > normalized_feature_std" , "==" , "True" ]
            ]
        }
}     
